kmviz/__init__.py
kmviz/__main__.py
kmviz/api.py
kmviz/app.py
kmviz/assets/_kmviz_instance_plugin_assets/placeholder.png
kmviz/assets/dashAgGridComponentFunctions.js
kmviz/assets/dmc.css
kmviz/assets/grid.css
kmviz/assets/kmviz.css
kmviz/assets/scroll.css
kmviz/core/__init__.py
kmviz/core/cache.py
kmviz/core/config.py
kmviz/core/io.py
kmviz/core/log.py
kmviz/core/metadata/__init__.py
kmviz/core/metadata/db.py
kmviz/core/metadata/mysql.py
kmviz/core/metadata/parquet.py
kmviz/core/metadata/sqlite.py
kmviz/core/metadata/tsv.py
kmviz/core/notifier/__init__.py
kmviz/core/notifier/azure.py
kmviz/core/notifier/notifier.py
kmviz/core/notifier/sendgrid.py
kmviz/core/notifier/smtp.py
kmviz/core/plugin.py
kmviz/core/provider/__init__.py
kmviz/core/provider/kmindex.py
kmviz/core/provider/options.py
kmviz/core/provider/provider.py
kmviz/core/provider/utils.py
kmviz/core/query/__init__.py
kmviz/core/query/query.py
kmviz/core/utils.py
kmviz/init.py
kmviz/ui/__init__.py
kmviz/ui/components/factory.py
kmviz/ui/components/helpers.py
kmviz/ui/components/option.py
kmviz/ui/id_factory.py
kmviz/ui/layouts/__init__.py
kmviz/ui/layouts/config.py
kmviz/ui/layouts/figure/__init__.py
kmviz/ui/layouts/figure/axe.py
kmviz/ui/layouts/figure/color.py
kmviz/ui/layouts/figure/download_graph.py
kmviz/ui/layouts/figure/legend.py
kmviz/ui/layouts/figure/map.py
kmviz/ui/layouts/figure/plot.py
kmviz/ui/layouts/figure/plotly.py
kmviz/ui/layouts/figure/shape.py
kmviz/ui/layouts/figure/slider.py
kmviz/ui/layouts/figure/title.py
kmviz/ui/layouts/filter.py
kmviz/ui/layouts/help.py
kmviz/ui/layouts/index.py
kmviz/ui/layouts/input.py
kmviz/ui/layouts/notif.py
kmviz/ui/layouts/sequence.py
kmviz/ui/layouts/session.py
kmviz/ui/layouts/sidebar.py
kmviz/ui/layouts/submit.py
kmviz/ui/layouts/table.py
kmviz/ui/layouts/tabs.py
kmviz/ui/pages/dashboard.py
kmviz/ui/pages/instance.py
kmviz/ui/presets.py
kmviz/ui/utils.py
kmviz-0.8.0.dist-info/LICENSE
kmviz-0.8.0.dist-info/METADATA
kmviz-0.8.0.dist-info/WHEEL
kmviz-0.8.0.dist-info/RECORD
